Metadata-Version: 1.1
Name: customize-notifications
Version: 1.0.0
Summary: customize notifications python sdk
Home-page: https://github.com/renjunok/customize-notifications-python-sdk
Author: renjun
Author-email: jamesbond.ren@gmail.com
License: UNKNOWN
Platform: UNKNOWN
Classifier: Programming Language :: Python :: 3
Classifier: License :: OSI Approved :: MIT License
Classifier: Operating System :: OS Independent
